twitterapi/__init__.py
twitterapi/api_client.py
twitterapi/config.py
twitterapi/mcp_server.py
twitterapi/utils.py
twitterapi/resources/__init__.py
twitterapi/resources/tweet_resources.py
twitterapi/resources/user_resources.py
twitterapi/tools/__init__.py
twitterapi/tools/basic_tools.py
twitterapi_mcp-0.1.4.dist-info/licenses/LICENSE
twitterapi_server/__init__.py
twitterapi_mcp-0.1.4.dist-info/METADATA
twitterapi_mcp-0.1.4.dist-info/WHEEL
twitterapi_mcp-0.1.4.dist-info/entry_points.txt
twitterapi_mcp-0.1.4.dist-info/top_level.txt
twitterapi_mcp-0.1.4.dist-info/RECORD
