Metadata-Version: 2.4
Name: twitterapi-mcp
Version: 0.1.4
Summary: TwitterAPI.io MCP Server for AI assistant access to Twitter data
Author-email: DevRico003 <devrico003@gmail.com>
License-Expression: MIT
Project-URL: Homepage, https://github.com/DevRico003/twitterapi.io-mcp
Project-URL: Bug Tracker, https://github.com/DevRico003/twitterapi.io-mcp/issues
Project-URL: Source Code, https://github.com/DevRico003/twitterapi.io-mcp
Keywords: twitter,api,mcp,llm,ai,assistant
Classifier: Development Status :: 4 - Beta
Classifier: Intended Audience :: Developers
Classifier: Programming Language :: Python :: 3
Classifier: Programming Language :: Python :: 3.8
Classifier: Programming Language :: Python :: 3.9
Classifier: Programming Language :: Python :: 3.10
Classifier: Programming Language :: Python :: 3.11
Classifier: Programming Language :: Python :: 3.12
Classifier: Topic :: Software Development :: Libraries :: Python Modules
Classifier: Topic :: Internet :: WWW/HTTP
Requires-Python: >=3.8
License-File: LICENSE
Requires-Dist: httpx>=0.23.0
Requires-Dist: mcp>=0.4.0
Requires-Dist: python-dotenv>=1.0.0
Provides-Extra: dev
Requires-Dist: pytest>=7.0.0; extra == "dev"
Requires-Dist: pytest-asyncio>=0.20.0; extra == "dev"
Dynamic: license-file
